kafka_handler/__init__.py
kafka_handler/handler.py
kafka_handler-1.0.4.dist-info/LICENSE
kafka_handler-1.0.4.dist-info/METADATA
kafka_handler-1.0.4.dist-info/WHEEL
kafka_handler-1.0.4.dist-info/top_level.txt
kafka_handler-1.0.4.dist-info/RECORD
